reactable/__init__.py
reactable/_render_gt.py
reactable/_tbl_data.py
reactable/models.py
reactable/models_js.py
reactable/options.py
reactable/render_gt.py
reactable/simpleframe.py
reactable/tags.py
reactable/widgets.py
reactable/data/__init__.py
reactable/data/cars_93.csv
reactable/data/co2.csv
reactable/data/nottem.csv
reactable/data/penguins.csv
reactable/data/sleep.csv
reactable/data/starwars.json
reactable/data/us_expenditure.csv
reactable/data/us_expenditures.csv
reactable/data/us_states.csv
reactable/static/reactable-py.esm.css
reactable/static/reactable-py.esm.js
reactable-0.1.6.dist-info/METADATA
reactable-0.1.6.dist-info/WHEEL
reactable-0.1.6.dist-info/top_level.txt
reactable-0.1.6.dist-info/RECORD
